polyhedra/ArchimedeanSolid.py
polyhedra/ConvexSolid.py
polyhedra/PlatonicSolid.py
polyhedra/Solid.py
polyhedra/__init__.py
polyhedra/tools.py
polyhedra-0.3.dist-info/METADATA
polyhedra-0.3.dist-info/WHEEL
polyhedra-0.3.dist-info/top_level.txt
polyhedra-0.3.dist-info/RECORD
