Metadata-Version: 2.1
Name: polyhedra
Version: 0.3
Summary: Various tools for manipulating 3D polyhedra and converting them to STL files.
Home-page: UNKNOWN
Author: Franklin Pezzuti Dyer
Author-email: franklin+polyhedra@dyer.me
License: UNKNOWN
Platform: UNKNOWN
Requires-Dist: numpy
Requires-Dist: os
